dig_ass_critic_protos/DigitalAssistantCritic_pb2.py
dig_ass_critic_protos/DigitalAssistantCritic_pb2.pyi
dig_ass_critic_protos/DigitalAssistantCritic_pb2_grpc.py
dig_ass_critic_protos/__init__.py
dig_ass_critic_protos/client.py
dig_ass_critic_protos-3.1.2.dist-info/METADATA
dig_ass_critic_protos-3.1.2.dist-info/WHEEL
dig_ass_critic_protos-3.1.2.dist-info/top_level.txt
dig_ass_critic_protos-3.1.2.dist-info/RECORD
